hackernews_mcp-0.1.3.dist-info/licenses/LICENSE
hackernews_mcp_service/__init__.py
hackernews_mcp_service/client.py
hackernews_mcp_service/mcp_server.py
hackernews_mcp-0.1.3.dist-info/METADATA
hackernews_mcp-0.1.3.dist-info/WHEEL
hackernews_mcp-0.1.3.dist-info/entry_points.txt
hackernews_mcp-0.1.3.dist-info/top_level.txt
hackernews_mcp-0.1.3.dist-info/RECORD
