Metadata-Version: 2.4
Name: hackernews-mcp
Version: 0.1.3
Summary: A service to fetch top Hacker News stories by comment count.
Author-email: AI Assistant <assistant@example.com>
Project-URL: Homepage, https://github.com/placeholder/hackernews-mcp-service
Classifier: Programming Language :: Python :: 3
Classifier: License :: OSI Approved :: MIT License
Classifier: Operating System :: OS Independent
Requires-Python: >=3.10
License-File: LICENSE
Requires-Dist: requests
Requires-Dist: mcp[cli]
Dynamic: license-file
